mm_base6/__init__.py
mm_base6/config.py
mm_base6/py.typed
mm_base6/run.py
mm_base6/core/__init__.py
mm_base6/core/core.py
mm_base6/core/db.py
mm_base6/core/errors.py
mm_base6/core/logger.py
mm_base6/core/service.py
mm_base6/core/utils.py
mm_base6/core/builtin_services/__init__.py
mm_base6/core/builtin_services/event.py
mm_base6/core/builtin_services/logfile.py
mm_base6/core/builtin_services/settings.py
mm_base6/core/builtin_services/stat.py
mm_base6/core/builtin_services/state.py
mm_base6/core/builtin_services/telegram.py
mm_base6/server/__init__.py
mm_base6/server/cbv.py
mm_base6/server/deps.py
mm_base6/server/jinja.py
mm_base6/server/server.py
mm_base6/server/utils.py
mm_base6/server/uvicorn.py
mm_base6/server/assets/base.css
mm_base6/server/assets/base.js
mm_base6/server/assets/sortable.min.js
mm_base6/server/middleware/__init__.py
mm_base6/server/middleware/auth.py
mm_base6/server/middleware/request_logging.py
mm_base6/server/routers/__init__.py
mm_base6/server/routers/api_method.py
mm_base6/server/routers/auth.py
mm_base6/server/routers/event.py
mm_base6/server/routers/settings.py
mm_base6/server/routers/state.py
mm_base6/server/routers/system.py
mm_base6/server/routers/ui.py
mm_base6/server/templates/events.j2
mm_base6/server/templates/login.j2
mm_base6/server/templates/settings.j2
mm_base6/server/templates/settings_multiline.j2
mm_base6/server/templates/settings_toml.j2
mm_base6/server/templates/state.j2
mm_base6/server/templates/state_update.j2
mm_base6/server/templates/system.j2
mm_base6/server/templates/inc/base.j2
mm_base6-0.8.2.dist-info/METADATA
mm_base6-0.8.2.dist-info/WHEEL
mm_base6-0.8.2.dist-info/RECORD
