Metadata-Version: 2.4
Name: mm-base6
Version: 0.8.2
Summary: Web framework with MongoDB integration and unified `self.core` access.
Requires-Python: >=3.14
Requires-Dist: fastapi[standard]~=0.128.0
Requires-Dist: itsdangerous~=2.2.0
Requires-Dist: mm-concurrency~=0.1.0
Requires-Dist: mm-jinja~=0.0.5
Requires-Dist: mm-mongo~=0.6.3
Requires-Dist: mm-std~=0.6.0
Requires-Dist: mm-telegram~=0.3.4
Requires-Dist: psutil~=7.2.1
Requires-Dist: pydantic-settings~=2.12.0
Requires-Dist: starlette~=0.50.0
Requires-Dist: tomlkit~=0.13.3
Requires-Dist: uvloop~=0.22.1
